{
  "collectionName": "components_medias_testtest_landscapes",
  "info": {
    "displayName": "testtestLandscape",
    "icon": "file"
  },
  "options": {},
  "attributes": {
    "testImg": {
      "allowedTypes": [
        "images",
        "files",
        "videos",
        "audios"
      ],
      "type": "media",
      "multiple": false
    },
    "testBackground": {
      "allowedTypes": [
        "images",
        "files",
        "videos",
        "audios"
      ],
      "type": "media",
      "multiple": false
    }
  }
}
